universql/__init__.py
universql/agent/__init__.py
universql/agent/cloudflared.py
universql/catalog/__init__.py
universql/catalog/iceberg.py
universql/lake/cloud.py
universql/lake/fsspec_util.py
universql/main.py
universql/plugin.py
universql/plugins/__init__.py
universql/plugins/snow.py
universql/plugins/ui.py
universql/protocol/__init__.py
universql/protocol/lambda.py
universql/protocol/session.py
universql/protocol/snowflake.py
universql/protocol/utils.py
universql/streamlit/.streamlit/config.toml
universql/streamlit/app.py
universql/streamlit/requirements.txt
universql/util.py
universql/warehouse/__init__.py
universql/warehouse/bigquery.py
universql/warehouse/duckdb.py
universql/warehouse/redshift.py
universql/warehouse/snowflake.py
universql-0.1.1.dev1742453945.dist-info/LICENSE
universql-0.1.1.dev1742453945.dist-info/METADATA
universql-0.1.1.dev1742453945.dist-info/WHEEL
universql-0.1.1.dev1742453945.dist-info/entry_points.txt
universql-0.1.1.dev1742453945.dist-info/RECORD
