Metadata-Version: 2.1
Name: universql
Version: 0.1.1.dev1742453945
Summary: 
Home-page: https://github.com/buremba/universql
License: Apache 2.0
Keywords: dbt,server,streamlit,git,refine,data-app,snowflake
Author: Burak Kabakcı
Author-email: emrekabakci@gmail.com
Requires-Python: >=3.11,<3.13
Classifier: License :: Other/Proprietary License
Classifier: Programming Language :: Python :: 3
Classifier: Programming Language :: Python :: 3.11
Requires-Dist: aws-cdk-aws-codestar-alpha (>=2.162.1a0,<3.0.0)
Requires-Dist: aws-cdk-lib (>=2.162.0,<3.0.0)
Requires-Dist: click (>7)
Requires-Dist: duckdb (>=1.1.3,<2.0.0)
Requires-Dist: duckdb-engine (>=0.13.2,<0.14.0)
Requires-Dist: fakesnow (>=0.9.27,<0.10.0)
Requires-Dist: fastapi (>=0.111.0,<0.112.0)
Requires-Dist: fsspec (>=2024.6.1,<2025.0.0)
Requires-Dist: gcsfs (>=2024.6.1,<2025.0.0)
Requires-Dist: google-cloud-bigquery (>=3.25.0,<4.0.0)
Requires-Dist: humanize (>=4.10.0,<5.0.0)
Requires-Dist: mangum (>=0.19.0,<0.20.0)
Requires-Dist: marimo (>=0.10.9,<0.11.0)
Requires-Dist: psutil (>=6.0.0,<7.0.0)
Requires-Dist: pyarrow (>=17.0.0,<18.0.0)
Requires-Dist: pyiceberg[glue,sql-sqlite] (>=0.7.1,<0.8.0)
Requires-Dist: s3fs (>=2024.6.1,<2025.0.0)
Requires-Dist: sentry-sdk[fastapi] (>=2.17.0,<3.0.0)
Requires-Dist: snowflake-connector-python[pandas,secure-local-storage] (>=3.12.0,<4.0.0)
Requires-Dist: sqlalchemy (>=2.0.35,<3.0.0)
Requires-Dist: sqlglot (>=25.34.0,<25.35.0)
Requires-Dist: uvicorn (>=0.30.1,<0.31.0)
Project-URL: Documentation, https://github.com/buremba/universql
Project-URL: Repository, https://github.com/buremba/universql
